{
    "name": "WordPress plugin: SkautIS integrace",
    "short-description": "Plugin pro WordPress, který napojuje přihlašování přes skautIS na skautské weby.",
    "description": "Plugin zajišťuje propojení skautských webů se skautISem. Dá se přes plugin registrovat, přihlašovat. Dokáže u stránek nastavovat oprávnění podle roli a dalších nastavení ve skautISu. Skrývá obsah podle toho jaká pravidla na stránce jsou nastavená.",
    "tags": [
        "wordpress",
        "php",
        "javascript",
        "skautis"
    ],
    "maintainers": [
        {
            "name": "Marek Dědič – Mlha",
            "email": "mlha@skaut.cz"
        }
    ],
    "links": [
        {
            "type": "email",
            "uri": "mailto:mlha@skaut.cz"
        },
        {
            "type": "homepage",
            "uri": "https://wordpress.org/plugins/skautis-integration/"
        },
        {
            "type": "issue-tracker",
            "uri": "https://github.com/skaut/skautis-integration/issues"
        },
        {
            "type": "docs",
            "uri": "https://napoveda.skaut.cz/skautis/skautis-integration"
        },
        {
            "type": "github-repo",
            "uri": "https://github.com/skaut/skautis-integration",
            "name": "skaut/skautis-integration"
        }
    ]
}
